py_menu/__init__.py
py_menu/examples/add_option_example.py
py_menu/examples/backtrack_example.py
py_menu/examples/custom_exits_example.py
py_menu/examples/low_level_example.py
py_menu/examples/pretty_menu_example.py
py_menu-1.2.1.dist-info/LICENSE
py_menu-1.2.1.dist-info/METADATA
py_menu-1.2.1.dist-info/WHEEL
py_menu-1.2.1.dist-info/top_level.txt
py_menu-1.2.1.dist-info/RECORD
