Metadata-Version: 2.1
Name: py-menu
Version: 1.2.1
Summary: Command-line driven menu interface in python
Home-page: https://github.com/SyntaxVoid/py_menu
Author: John Gresl
Author-email: j.gresl12@gmail.com
License: UNKNOWN
Platform: UNKNOWN
Classifier: Programming Language :: Python :: 3
Classifier: License :: OSI Approved :: MIT License
Classifier: Operating System :: OS Independent
Classifier: Development Status :: 5 - Production/Stable
Classifier: Environment :: Console
Requires-Python: >=3.0
